qoqo_qiskit/__init__.py
qoqo_qiskit/models.py
qoqo_qiskit/backend/__init__.py
qoqo_qiskit/backend/backend.py
qoqo_qiskit/backend/post_processing.py
qoqo_qiskit/backend/queued_results.py
qoqo_qiskit/backend/utils.py
qoqo_qiskit/interface/__init__.py
qoqo_qiskit/interface/interface.py
qoqo_qiskit/transpiler_helper/__init__.py
qoqo_qiskit/transpiler_helper/transpiler_helper.py
qoqo_qiskit-0.10.1.dist-info/licenses/LICENSE
qoqo_qiskit-0.10.1.dist-info/METADATA
qoqo_qiskit-0.10.1.dist-info/WHEEL
qoqo_qiskit-0.10.1.dist-info/top_level.txt
qoqo_qiskit-0.10.1.dist-info/RECORD
