Metadata-Version: 2.4
Name: qoqo_qiskit
Version: 0.10.1
Author-email: HQS Quantum Simulation GmbH <info@quantumsimulations.de>
Maintainer-email: Matteo Lodi <matteo.lodi@quantumsimulations.de>
License:                                  Apache License
Requires-Python: >=3.9
License-File: LICENSE
Requires-Dist: qoqo<1.20,>=1.19
Requires-Dist: qoqo_qasm<0.13,>=0.12.1
Requires-Dist: qiskit<1.3,>=1.0
Requires-Dist: qiskit_aer>=0.15
Requires-Dist: qiskit_ibm_runtime<0.36,>=0.35
Requires-Dist: numpy
Provides-Extra: tests
Requires-Dist: coverage; extra == "tests"
Requires-Dist: pytest; extra == "tests"
Requires-Dist: pytest-cov; extra == "tests"
Provides-Extra: dev
Requires-Dist: bandit; extra == "dev"
Requires-Dist: black; extra == "dev"
Requires-Dist: mypy; extra == "dev"
Requires-Dist: ruff; extra == "dev"
Provides-Extra: doc
Requires-Dist: sphinx; extra == "doc"
Requires-Dist: sphinx_rtd_theme; extra == "doc"
Requires-Dist: nbsphinx; extra == "doc"
Dynamic: license-file
